<?xml version="1.0" encoding="utf-8"?>
<!DOCTYPE Annotation>
<?xml-stylesheet type="text/css" href="GENIA_tree_bracket.css"?>
<Annotation>
<PubmedArticleSet>
<PubmedArticle>
<MedlineCitation>
<PMID>10322160</PMID>
<Article>
<ArticleTitle><sentence id="S1"><cons cat="NP"><cons cat="NP"><tok cat="NN">Control</tok></cons> <cons cat="PP"><tok cat="IN">of</tok> <cons cat="NP"><tok cat="NN">lymphocyte</tok> <tok cat="NN">development</tok></cons></cons> <cons cat="PP"><tok cat="IN">by</tok> <cons cat="NP"><tok cat="DT">the</tok> <tok cat="NN">Ikaros</tok> <tok cat="NN">gene</tok> <tok cat="NN">family</tok></cons></cons><tok cat="PERIOD">.</tok></cons></sentence></ArticleTitle>
<Abstract>
<AbstractText><sentence id="S2"><cons cat="S"><cons cat="NP" role="SBJ"><tok cat="JJ">Lymphoid</tok> <tok cat="NN">cell</tok> <tok cat="NN">differentiation</tok></cons> <cons cat="VP"><tok cat="VBZ">relies</tok> <cons cat="PP"><tok cat="IN">on</tok> <cons cat="NP" syn="COOD"><cons cat="ADJP"><tok cat="RB">precisely</tok> <tok cat="VBN">orchestrated</tok></cons> <cons cat="NP"><tok cat="NN">gene</tok> <tok cat="NN">activation</tok></cons> <tok cat="CC">and</tok> <cons cat="NP"><tok cat="NN">repression</tok> <tok cat="NNS">events</tok></cons></cons></cons></cons><tok cat="PERIOD">.</tok></cons></sentence>
<sentence id="S3"><cons cat="S"><cons cat="NP" role="SBJ"><tok cat="NN">Gene</tok> <tok cat="NN">targeting</tok> <tok cat="NNS">studies</tok></cons> <cons cat="VP"><tok cat="VBP">have</tok> <cons cat="VP"><tok cat="VBN">demonstrated</tok> <cons cat="NP"><cons cat="NP"><tok cat="JJ">crucial</tok> <tok cat="NNS">roles</tok></cons> <cons cat="PP"><tok cat="IN">for</tok> <cons cat="NP"><tok cat="DT">the</tok> <cons cat="NP"><tok cat="NN">transcription</tok> <tok cat="NNS">factors</tok></cons> <cons cat="NP" syn="COOD"><cons cat="NP"><tok cat="NN">Ikaros</tok></cons> <tok cat="CC">and</tok> <cons cat="NP"><tok cat="NN">Aiolos</tok></cons></cons></cons></cons> <cons cat="PP"><tok cat="IN">in</tok> <cons cat="S"><cons cat="NP" role="SBJ" null="NONE"></cons><cons cat="VP"><tok cat="VBG">regulating</tok> <cons cat="NP"><cons cat="NP"><tok cat="JJ">multiple</tok> <tok cat="NNS">stages</tok></cons> <cons cat="PP"><tok cat="IN">of</tok> <cons cat="NP" syn="COOD"><cons cat="NP"><tok cat="NN">B</tok> <cons cat="NP" ref="i1" null="RNR"></cons></cons><tok cat="CC">and</tok> <cons cat="NP"><tok cat="NN">T</tok> <cons cat="NP" ref="i1" null="RNR"></cons></cons><cons cat="NP" id="i1"><tok cat="NN">cell</tok> <tok cat="NN">development</tok></cons></cons></cons></cons></cons></cons></cons></cons></cons></cons><tok cat="PERIOD">.</tok></cons></sentence>
<sentence id="S4"><cons cat="S"><cons cat="NP" role="SBJ"><tok cat="JJ">Recent</tok> <tok cat="NNS">experiments</tok></cons> <cons cat="VP"><tok cat="VBP">suggest</tok> <cons cat="SBAR" syn="COOD"><cons cat="SBAR"><tok cat="IN">that</tok> <cons cat="S"><cons cat="NP" syn="COOD" role="SBJ"><cons cat="NP"><tok cat="NN">Ikaros</tok></cons> <tok cat="CC">and</tok> <cons cat="NP"><tok cat="NN">Aiolos</tok></cons></cons> <cons cat="VP"><tok cat="VBP">set</tok> <cons cat="NP"><cons cat="ADJP" syn="COOD"><cons cat="ADJP"><tok cat="NN">B</tok> <tok cat="NN">cell</tok> <tok cat="NN">antigen-receptor</tok> <tok cat="LRB">(</tok><tok cat="NN">BCR</tok><tok cat="RRB">)</tok><tok cat="COLON">-</tok> <cons cat="ADJP" null="QSTN"></cons></cons><tok cat="CC">and</tok> <cons cat="ADJP"><tok cat="JJ">TCR-mediated</tok></cons></cons> <cons cat="NP"><tok cat="NN">signaling</tok> <tok cat="NNS">thresholds</tok></cons></cons></cons></cons></cons> <tok cat="CC">and</tok> <cons cat="SBAR"><tok cat="IN">that</tok> <cons cat="S"><cons cat="NP" role="SBJ"><tok cat="DT">the</tok> <tok cat="NNS">molecules</tok></cons> <cons cat="VP"><tok cat="VBP">exist</tok> <cons cat="PP"><tok cat="IN">within</tok> <cons cat="NP"><cons cat="NP"><tok cat="NN">T</tok> <tok cat="NNS">cells</tok></cons> <cons cat="PP"><tok cat="IN">in</tok> <cons cat="NP"><cons cat="NP"><tok cat="JJ">nuclear</tok> <tok cat="NNS">complexes</tok></cons> <cons cat="SBAR"><cons cat="WHNP" id="i3"><tok cat="WDT">that</tok></cons> <cons cat="S"><cons cat="NP" ref="i3" role="SBJ" null="T"></cons><cons cat="VP"><tok cat="VBP">contain</tok> <cons cat="NP" syn="COOD"><cons cat="NP"><tok cat="JJ">nucleosome</tok> <tok cat="NN">remodeling</tok></cons> <tok cat="CC">and</tok> <cons cat="NP"><tok cat="NN">histone</tok> <tok cat="NN">deacetylase</tok> <tok cat="NNS">activities</tok></cons></cons></cons></cons></cons></cons></cons></cons></cons></cons></cons></cons></cons></cons><tok cat="PERIOD">.</tok></cons></sentence></AbstractText>
</Abstract>
</Article>
</MedlineCitation>
</PubmedArticle>
</PubmedArticleSet>
</Annotation>
