<?xml version="1.0" encoding="utf-8"?>
<!DOCTYPE Annotation>
<?xml-stylesheet type="text/css" href="GENIA_tree_bracket.css"?>
<Annotation>
<PubmedArticleSet>
<PubmedArticle>
<MedlineCitation>
<PMID>10455523</PMID>
<Article>
<ArticleTitle><sentence id="S1"><cons cat="NP" syn="COOD"><cons cat="NP"><tok cat="NN">Gender</tok></cons> <tok cat="CC">and</tok> <cons cat="NP"><tok cat="JJ">vascular</tok> <tok cat="NN">reactivity</tok></cons><tok cat="PERIOD">.</tok></cons></sentence></ArticleTitle>
<Abstract>
<AbstractText><sentence id="S2"><cons cat="S"><cons cat="S"><cons cat="NP" id="i1" role="SBJ"><tok cat="NN">Estrogen</tok> <tok cat="NNS">receptors</tok></cons> <cons cat="VP"><tok cat="VBP">are</tok> <cons cat="VP"><tok cat="VBN">found</tok> <cons cat="NP" ref="i1" null="NONE"></cons><cons cat="PP"><tok cat="IN">on</tok> <cons cat="NP" syn="COOD"><cons cat="NP"><tok cat="JJ">vascular</tok> <tok cat="JJ">endothelial</tok> <cons cat="NP" ref="i2" null="RNR"></cons></cons><tok cat="CC">and</tok> <cons cat="NP"><tok cat="VB">smooth</tok> <tok cat="NN">muscle</tok> <cons cat="NP" ref="i2" null="RNR"></cons></cons><cons cat="NP" id="i2"><tok cat="NNS">cells</tok></cons></cons></cons></cons></cons><tok cat="COLON">;</tok></cons> <cons cat="S"><cons cat="NP" id="i3" role="SBJ"><tok cat="PRPP">their</tok> <tok cat="NN">expression</tok></cons> <cons cat="VP"><tok cat="VBZ">is</tok> <cons cat="VP"><tok cat="VBN">influenced</tok> <cons cat="NP" ref="i3" null="NONE"></cons><cons cat="PP"><tok cat="IN">by</tok> <cons cat="NP" role="LGS"><cons cat="NP"><tok cat="NN">exposure</tok></cons> <cons cat="PP"><tok cat="TO">to</tok> <cons cat="NP"><tok cat="DT">the</tok> <tok cat="NN">hormone</tok></cons></cons></cons></cons></cons></cons></cons><tok cat="PERIOD">.</tok></cons></sentence>
<sentence id="S3"><cons cat="S"><cons cat="NP" role="SBJ"><tok cat="NN">Estrogen</tok> <tok cat="NNS">receptors</tok></cons> <cons cat="VP"><tok cat="VBP">influence</tok> <cons cat="NP" syn="COOD"><cons cat="NP"><cons cat="NP"><tok cat="JJ">non-genomic</tok> <tok cat="NNS">events</tok></cons><tok cat="COMMA">,</tok> <cons cat="SBAR"><cons cat="WHNP" id="i4"><tok cat="WDT">which</tok></cons> <cons cat="S"><cons cat="NP" ref="i4" role="SBJ" null="T"></cons><cons cat="VP"><tok cat="VBP">are</tok> <cons cat="ADJP" role="PRD"><tok cat="JJ">rapid</tok> <cons cat="PP"><tok cat="IN">in</tok> <cons cat="NP"><tok cat="NN">onset</tok></cons></cons></cons></cons></cons></cons></cons> <tok cat="CC">and</tok> <cons cat="NP"><cons cat="NP"><tok cat="JJ">genomic</tok> <tok cat="NNS">events</tok></cons><tok cat="COMMA">,</tok> <cons cat="SBAR"><cons cat="WHNP" id="i5"><tok cat="WDT">which</tok></cons> <cons cat="S"><cons cat="NP" ref="i5" role="SBJ" null="T"></cons><cons cat="VP"><tok cat="VBP">are</tok> <cons cat="NP" role="PRD"><tok cat="RBR">longer</tok> <tok cat="NN">acting</tok> <tok cat="NNS">responses</tok></cons></cons></cons></cons></cons></cons></cons><tok cat="PERIOD">.</tok></cons></sentence>
<sentence id="S4"><cons cat="S"><cons cat="NP" role="SBJ"><tok cat="NNS">Estrogens</tok></cons> <cons cat="VP"><tok cat="VBP">affect</tok> <cons cat="NP"><tok cat="JJ">vascular</tok> <tok cat="NN">tone</tok></cons> <cons cat="PP" syn="COOD"><cons cat="ADVP"><tok cat="RB">indirectly</tok></cons> <cons cat="PP"><tok cat="IN">by</tok> <cons cat="S"><cons cat="NP" role="SBJ" null="NONE"></cons><cons cat="VP"><tok cat="VBG">modulating</tok> <cons cat="NP"><cons cat="NP"><tok cat="NN">release</tok></cons> <cons cat="PP"><tok cat="IN">of</tok> <cons cat="NP"><tok cat="JJ">endothelium-derived</tok> <tok cat="JJ">vasoactive</tok> <tok cat="NNS">factors</tok></cons></cons></cons></cons></cons></cons> <tok cat="CC">and</tok> <cons cat="ADVP"><tok cat="RB">directly</tok></cons> <cons cat="PP"><tok cat="IN">by</tok> <cons cat="S"><cons cat="NP" role="SBJ" null="NONE"></cons><cons cat="VP"><tok cat="VBG">modulating</tok> <cons cat="NP"><tok cat="JJ">intracellular</tok> <tok cat="NN">calcium</tok></cons> <cons cat="PP"><tok cat="IN">in</tok> <cons cat="NP"><tok cat="JJ">vascular</tok> <tok cat="NN">smooth</tok> <tok cat="NN">muscle</tok> <tok cat="NNS">cells</tok></cons></cons></cons></cons></cons></cons></cons><tok cat="PERIOD">.</tok></cons></sentence>
<sentence id="S5"><cons cat="S"><cons cat="NP" role="SBJ"><tok cat="NNS">Estrogens</tok></cons> <cons cat="ADVP"><tok cat="RB">indirectly</tok></cons> <cons cat="VP"><tok cat="VBP">affect</tok> <cons cat="NP" syn="COOD"><cons cat="NP"><tok cat="JJ">thrombotic</tok> <tok cat="NNS">events</tok></cons> <tok cat="CC">and</tok> <cons cat="NP"><tok cat="NN">inflammation</tok></cons></cons> <cons cat="PP"><tok cat="IN">by</tok> <cons cat="S"><cons cat="NP" role="SBJ" null="NONE"></cons><cons cat="VP"><tok cat="VBG">altering</tok> <cons cat="NP" syn="COOD"><cons cat="NP"><tok cat="NN">platelet</tok> <tok cat="NN">aggregation</tok></cons> <tok cat="CC">and</tok> <cons cat="NP"><tok cat="NN">leukocyte</tok> <cons cat="NP" syn="COOD"><cons cat="NP"><tok cat="NN">adherence</tok></cons> <tok cat="CC">and</tok> <cons cat="NP"><tok cat="NN">migration</tok></cons></cons></cons></cons><tok cat="COMMA">,</tok> <cons cat="ADVP"><tok cat="RB">respectively</tok></cons></cons></cons></cons></cons><tok cat="PERIOD">.</tok></cons></sentence>
<sentence id="S6"><cons cat="S"><cons cat="NP" role="SBJ"><tok cat="NNS">Estrogens</tok></cons> <cons cat="ADVP"><tok cat="RB">also</tok></cons> <cons cat="VP"><tok cat="VBP">influence</tok> <cons cat="NP"><cons cat="NP"><tok cat="NN">production</tok></cons> <cons cat="PP"><tok cat="IN">of</tok> <cons cat="NP"><cons cat="NP"><tok cat="NNS">mitogens</tok></cons> <cons cat="SBAR"><cons cat="WHNP" id="i6"><tok cat="WDT">which</tok></cons><tok cat="COMMA">,</tok> <cons cat="S"><cons cat="SBAR" adv="TMP"><tok cat="WRB">when</tok> <cons cat="S"><cons cat="NP" id="i7" role="SBJ" null="NONE"></cons><cons cat="VP"><tok cat="VBN">released</tok> <cons cat="NP" ref="i7" null="NONE"></cons><cons cat="PP"><tok cat="IN">at</tok> <cons cat="NP"><cons cat="NP"><tok cat="NNS">sites</tok></cons> <cons cat="PP"><tok cat="IN">of</tok> <cons cat="NP"><tok cat="JJ">vascular</tok> <tok cat="NN">injury</tok></cons></cons></cons></cons></cons></cons></cons><tok cat="COMMA">,</tok> <cons cat="NP" ref="i6" role="SBJ" null="T"></cons><cons cat="VP"><tok cat="VBP">affect</tok> <cons cat="NP"><tok cat="JJ">vascular</tok> <tok cat="NN">remodeling</tok></cons></cons></cons></cons></cons></cons></cons></cons><tok cat="PERIOD">.</tok></cons></sentence>
<sentence id="S7"><cons cat="S"><cons cat="SBAR" func="ADV"><tok cat="IN">Although</tok> <cons cat="S"><cons cat="NP" role="SBJ"><tok cat="NNS">estrogens</tok></cons> <cons cat="VP"><tok cat="VBP">initiate</tok> <cons cat="NP"><tok cat="JJ">vascular</tok> <tok cat="NNS">responses</tok></cons></cons></cons></cons><tok cat="COMMA">,</tok> <cons cat="NP" role="SBJ"><tok cat="JJ">genomic</tok> <tok cat="NN">sex</tok></cons> <cons cat="VP"><tok cat="MD">may</tok> <cons cat="VP" syn="COOD"><cons cat="VP"><tok cat="VB">influence</tok> <cons cat="NP" ref="i8" null="RNR"></cons><cons cat="PP" ref="i9" null="RNR"></cons></cons><tok cat="CC">and/or</tok> <cons cat="VP"><tok cat="VB">limit</tok> <cons cat="NP" ref="i8" null="RNR"></cons><cons cat="PP" ref="i9" null="RNR"></cons></cons><cons cat="NP" syn="COOD" id="i8"><cons cat="NP"><cons cat="NP"><tok cat="NN">expression</tok></cons> <cons cat="PP"><tok cat="IN">of</tok> <cons cat="NP"><tok cat="NN">estrogen</tok> <tok cat="NNS">receptors</tok></cons></cons></cons> <tok cat="CC">and</tok> <cons cat="ADVP"><tok cat="RB">therefore</tok></cons> <cons cat="NP"><cons cat="NP"><tok cat="NNS">actions</tok></cons> <cons cat="PP"><tok cat="IN">of</tok> <cons cat="NP"><tok cat="NN">sex</tok> <tok cat="NN">steroid</tok> <tok cat="NNS">hormones</tok></cons></cons></cons></cons> <cons cat="PP" id="i9"><tok cat="IN">throughout</tok> <cons cat="NP"><tok cat="DT">the</tok> <tok cat="NN">vasculature</tok></cons></cons></cons></cons><tok cat="PERIOD">.</tok></cons></sentence></AbstractText>
</Abstract>
</Article>
</MedlineCitation>
</PubmedArticle>
</PubmedArticleSet>
</Annotation>
