<?xml version="1.0" encoding="utf-8"?>
<!DOCTYPE Annotation>
<?xml-stylesheet type="text/css" href="GENIA_tree_bracket.css"?>
<Annotation>
<PubmedArticleSet>
<PubmedArticle>
<MedlineCitation>
<PMID>9285527</PMID>
<Article>
<ArticleTitle><sentence id="S1"><cons cat="S"><cons cat="S"><cons cat="NP" id="i5" role="SBJ"><cons cat="NP"><tok cat="DT">The</tok> <cons cat="NP"><tok cat="JJ">carboxyl-terminal</tok> <tok cat="JJ">cytoplasmic</tok> <tok cat="NN">domain</tok></cons></cons> <cons cat="PP"><tok cat="IN">of</tok> <cons cat="NP"><tok cat="NN">CD36</tok></cons></cons></cons> <cons cat="VP"><tok cat="VBZ">is</tok> <cons cat="VP"><tok cat="VBN">required</tok> <cons cat="NP" ref="i5" null="NONE"></cons><cons cat="PP"><tok cat="IN">for</tok> <cons cat="NP"><cons cat="NP"><tok cat="VBN">oxidized</tok> <tok cat="JJ">low-density</tok> <tok cat="NN">lipoprotein</tok> <tok cat="NN">modulation</tok></cons> <cons cat="PP"><tok cat="IN">of</tok> <cons cat="NP"><cons cat="NP"><cons cat="NP"><tok cat="NN">NF-kappaB</tok></cons> <tok cat="NN">activity</tok></cons> <cons cat="PP"><tok cat="IN">by</tok> <cons cat="NP" role="LGS"><tok cat="NN">tumor</tok> <tok cat="NN">necrosis</tok> <tok cat="NN">factor-alpha</tok></cons></cons></cons></cons></cons></cons></cons></cons><tok cat="PERIOD">.</tok></cons></cons></sentence></ArticleTitle>
<Abstract>
<AbstractText><sentence id="S2"><cons cat="S"><cons cat="S"><cons cat="NP" id="i6" role="SBJ"><cons cat="NP"><tok cat="DT">The</tok> <tok cat="NN">binding</tok></cons> <cons cat="PP"><tok cat="IN">of</tok> <cons cat="NP"><cons cat="NP"><tok cat="VBN">oxidized</tok> <tok cat="JJ">low-density</tok> <tok cat="NN">lipoprotein</tok></cons> <cons cat="PRN"><tok cat="LRB">(</tok><cons cat="NP"><tok cat="NN">Ox</tok> <tok cat="NN">LDL</tok></cons><tok cat="RRB">)</tok></cons></cons></cons> <cons cat="PP"><tok cat="IN">by</tok> <cons cat="NP" role="LGS"><tok cat="NNS">monocyte-macrophages</tok></cons></cons></cons> <cons cat="VP" syn="COOD"><cons cat="VP"><tok cat="VBZ">causes</tok> <cons cat="NP"><cons cat="NP"><tok cat="JJ">pleiotropic</tok> <tok cat="NNS">effects</tok></cons><tok cat="COMMA">,</tok> <cons cat="PP"><tok cat="VBG">including</tok> <cons cat="NP"><cons cat="NP"><tok cat="NNS">changes</tok></cons> <cons cat="PP"><tok cat="IN">in</tok> <cons cat="NP"><tok cat="NN">gene</tok> <tok cat="NN">expression</tok></cons></cons></cons></cons></cons></cons><tok cat="COMMA">,</tok> <tok cat="CC">and</tok> <cons cat="VP"><tok cat="VBZ">is</tok> <cons cat="VP"><tok cat="VBN">thought</tok> <cons cat="S"><cons cat="NP" ref="i6" role="SBJ" null="NONE"></cons><cons cat="VP"><tok cat="TO">to</tok> <cons cat="VP"><tok cat="VB">represent</tok> <cons cat="NP"><cons cat="NP"><tok cat="DT">an</tok> <tok cat="JJ">early</tok> <tok cat="NN">event</tok></cons> <cons cat="PP"><tok cat="IN">in</tok> <cons cat="NP"><tok cat="NN">atherogenesis</tok></cons></cons></cons></cons></cons></cons></cons></cons></cons><tok cat="PERIOD">.</tok></cons></cons></sentence>
<sentence id="S3"><cons cat="S"><cons cat="NP" id="i7" role="SBJ"><tok cat="DT">The</tok> <tok cat="JJ">integral</tok> <tok cat="NN">membrane</tok> <cons cat="NP"><tok cat="NN">glycoprotein</tok> <tok cat="NN">CD36</tok></cons></cons> <cons cat="VP"><tok cat="VBZ">appears</tok> <cons cat="S"><cons cat="NP" ref="i7" role="SBJ" null="NONE"></cons><cons cat="VP"><tok cat="TO">to</tok> <cons cat="VP"><tok cat="VB">play</tok> <cons cat="NP"><tok cat="DT">a</tok> <tok cat="JJ">physiological</tok> <tok cat="NN">role</tok></cons> <cons cat="PP"><tok cat="IN">in</tok> <cons cat="NP"><cons cat="NP" syn="COOD"><cons cat="NP"><tok cat="NN">binding</tok></cons> <tok cat="CC">and</tok> <cons cat="NP"><tok cat="NN">uptake</tok></cons></cons> <cons cat="PP"><tok cat="IN">of</tok> <cons cat="NP"><tok cat="NN">Ox</tok> <tok cat="NN">LDL</tok></cons></cons> <cons cat="PP"><tok cat="IN">by</tok> <cons cat="NP" role="LGS"><tok cat="NNS">monocyte-macrophages</tok></cons></cons></cons></cons></cons></cons></cons><tok cat="COMMA">,</tok> <cons cat="SBAR" func="ADV"><tok cat="IN">although</tok> <cons cat="S"><cons cat="NP" role="SBJ"><cons cat="NP"><tok cat="DT">the</tok> <tok cat="JJ">molecular</tok> <tok cat="NNS">events</tok></cons> <cons cat="VP"><tok cat="VBN">associated</tok> <cons cat="NP" null="NONE"></cons><cons cat="PP"><tok cat="IN">with</tok> <cons cat="NP"><tok cat="NN">CD36-Ox</tok> <tok cat="NN">LDL</tok> <tok cat="NN">interaction</tok></cons></cons></cons></cons> <cons cat="VP"><tok cat="VBP">are</tok> <cons cat="ADJP" role="PRD"><tok cat="JJ">unknown</tok></cons></cons></cons></cons></cons><tok cat="PERIOD">.</tok></cons></sentence>
<sentence id="S4"><cons cat="S"><cons cat="S" func="ADV"><cons cat="NP" ref="i8" role="SBJ" null="NONE"></cons><cons cat="VP"><tok cat="TO">To</tok> <cons cat="VP"><tok cat="VB">approach</tok> <cons cat="NP"><tok cat="DT">this</tok> <tok cat="NN">issue</tok></cons></cons></cons></cons><tok cat="COMMA">,</tok> <cons cat="S"><cons cat="NP" id="i8" role="SBJ"><tok cat="PRP">we</tok></cons> <cons cat="VP" syn="COOD"><cons cat="VP"><tok cat="VBD">used</tok> <cons cat="NP"><cons cat="NP"><tok cat="NN">CD36</tok></cons> <tok cat="JJ">transfected</tok> <cons cat="NP"><tok cat="JJ">Chinese</tok> <tok cat="NN">hampster</tok> <tok cat="NN">ovary</tok> <tok cat="LRB">(</tok><tok cat="NN">CHO</tok><tok cat="RRB">)</tok> <tok cat="NNS">cells</tok></cons></cons></cons><tok cat="COMMA">,</tok> <cons cat="VP"><tok cat="VBD">exposed</tok> <cons cat="NP"><tok cat="PRP">them</tok></cons> <cons cat="PP"><tok cat="TO">to</tok> <cons cat="NP"><tok cat="NN">Ox</tok> <tok cat="NN">LDL</tok></cons></cons></cons><tok cat="COMMA">,</tok> <tok cat="CC">and</tok> <cons cat="VP"><tok cat="VBD">determined</tok> <cons cat="NP"><cons cat="NP"><tok cat="NNS">changes</tok></cons> <cons cat="PP"><tok cat="IN">in</tok> <cons cat="NP"><cons cat="NP"><tok cat="DT">the</tok> <tok cat="NN">activity</tok></cons> <cons cat="PP"><tok cat="IN">of</tok> <cons cat="NP"><cons cat="NP"><tok cat="DT">the</tok> <cons cat="NP"><tok cat="NN">transcription</tok> <tok cat="NN">factor</tok></cons></cons> <cons cat="NP"><tok cat="NN">NF-kappaB</tok></cons></cons></cons></cons></cons></cons></cons></cons></cons><tok cat="PERIOD">.</tok></cons></sentence>
<sentence id="S5"><cons cat="S"><cons cat="NP" role="SBJ"><tok cat="PRP">We</tok></cons> <cons cat="VP"><tok cat="VBP">report</tok> <cons cat="ADVP"><tok cat="RB">here</tok></cons> <cons cat="SBAR"><tok cat="IN">that</tok> <cons cat="S"><cons cat="NP" role="SBJ"><tok cat="NN">Ox</tok> <tok cat="NN">LDL</tok></cons> <cons cat="VP"><tok cat="VBD">enhanced</tok> <cons cat="NP"><cons cat="NP"><tok cat="NN">DNA</tok> <tok cat="NN">binding</tok> <tok cat="NN">activity</tok></cons> <cons cat="PP"><tok cat="IN">of</tok> <cons cat="NP"><tok cat="JJ">nuclear</tok> <tok cat="NNS">extracts</tok></cons></cons> <cons cat="PP"><tok cat="TO">to</tok> <cons cat="NP"><tok cat="DT">an</tok> <cons cat="NP"><tok cat="NN">NF-kappaB</tok> <tok cat="NN">sequence</tok></cons></cons></cons></cons> <cons cat="PP"><tok cat="VBG">following</tok> <cons cat="NP"><cons cat="NP"><tok cat="NN">activation</tok></cons> <cons cat="PP"><tok cat="IN">of</tok> <cons cat="NP"><tok cat="JJ">CD36-producing</tok> <tok cat="NN">CHO</tok> <tok cat="NNS">cells</tok></cons></cons> <cons cat="PP"><tok cat="IN">with</tok> <cons cat="NP"><cons cat="NP"><tok cat="DT">the</tok> <cons cat="NP"><tok cat="JJ">proinflammatory</tok> <tok cat="NN">cytokine</tok></cons></cons> <cons cat="NP"><cons cat="NP"><tok cat="NN">tumor</tok> <tok cat="NN">necrosis</tok> <tok cat="NN">factor-alpha</tok></cons> <cons cat="PRN"><tok cat="LRB">(</tok><cons cat="NP"><tok cat="NN">TNF-alpha</tok></cons><tok cat="RRB">)</tok></cons></cons></cons></cons></cons></cons></cons></cons></cons></cons><tok cat="PERIOD">.</tok></cons></sentence>
<sentence id="S6"><cons cat="S"><cons cat="NP" id="i9" role="SBJ"><tok cat="DT">This</tok> <tok cat="VBN">enhanced</tok> <tok cat="NN">DNA</tok> <tok cat="NN">binding</tok> <tok cat="NN">activity</tok></cons> <cons cat="VP"><tok cat="VBD">was</tok> <cons cat="VP"><tok cat="VBN">inhibited</tok> <cons cat="NP" ref="i9" null="NONE"></cons><cons cat="PP"><tok cat="IN">by</tok> <cons cat="NP" role="LGS"><cons cat="NP"><tok cat="NN">coincubation</tok></cons> <cons cat="PP"><tok cat="IN">of</tok> <cons cat="NP"><cons cat="NP"><tok cat="NN">CD36</tok></cons> <tok cat="VBN">transfected</tok> <tok cat="NNS">cells</tok></cons></cons> <cons cat="PP"><tok cat="IN">with</tok> <cons cat="NP"><cons cat="NP"><tok cat="DT">the</tok> <cons cat="NP"><tok cat="JJ">human</tok> <tok cat="JJ">CD36-specific</tok> <tok cat="NN">antibody</tok></cons></cons> <cons cat="NP"><tok cat="NN">OKM5</tok></cons></cons></cons></cons></cons></cons></cons><tok cat="PERIOD">.</tok></cons></sentence>
<sentence id="S7"><cons cat="S"><cons cat="NP" role="SBJ"><tok cat="PRP">We</tok></cons> <cons cat="ADVP"><tok cat="RB">also</tok></cons> <cons cat="VP"><tok cat="VBD">determined</tok> <cons cat="SBAR"><tok cat="IN">that</tok> <cons cat="S"><cons cat="NP" role="SBJ"><cons cat="NP"><tok cat="NN">activation</tok></cons> <cons cat="PP"><tok cat="IN">of</tok> <cons cat="NP"><cons cat="NP"><tok cat="NN">NF-kappaB</tok></cons> <tok cat="NN">DNA</tok> <tok cat="NN">binding</tok> <tok cat="NN">activity</tok></cons></cons></cons> <cons cat="VP"><tok cat="VBD">required</tok> <cons cat="NP"><cons cat="NP"><tok cat="DT">an</tok> <tok cat="JJ">intact</tok> <cons cat="NP"><tok cat="JJ">carboxyl-terminal</tok> <tok cat="JJ">cytoplasmic</tok> <tok cat="NN">segment</tok></cons></cons> <cons cat="PP"><tok cat="IN">on</tok> <cons cat="NP"><tok cat="NN">CD36</tok></cons></cons></cons></cons></cons></cons></cons><tok cat="PERIOD">.</tok></cons></sentence>
<sentence id="S8"><cons cat="S"><cons cat="NP" role="SBJ"><tok cat="PRPP">Our</tok> <tok cat="NNS">results</tok></cons> <cons cat="VP"><tok cat="VBP">support</tok> <cons cat="NP"><tok cat="DT">the</tok> <tok cat="NN">idea</tok> <cons cat="SBAR"><tok cat="IN">that</tok> <cons cat="S"><cons cat="NP" role="SBJ"><tok cat="JJ">human</tok> <tok cat="NN">CD36</tok></cons> <cons cat="VP"><tok cat="VBZ">mediates</tok> <cons cat="NP"><tok cat="NN">signal</tok> <tok cat="NN">transduction</tok> <tok cat="NNS">events</tok></cons> <cons cat="PP"><tok cat="IN">in</tok> <cons cat="NP"><cons cat="NP"><tok cat="NN">response</tok></cons> <cons cat="PP"><tok cat="TO">to</tok> <cons cat="NP"><tok cat="NN">Ox</tok> <tok cat="NN">LDL</tok></cons></cons></cons></cons></cons></cons></cons></cons></cons><tok cat="PERIOD">.</tok></cons></sentence></AbstractText>
</Abstract>
</Article>
</MedlineCitation>
</PubmedArticle>
</PubmedArticleSet>
</Annotation>
